isNumberFour/__init__.py
isNumberFour/main.py
isNumberFour-0.2.0.dist-info/LICENSE
isNumberFour-0.2.0.dist-info/METADATA
isNumberFour-0.2.0.dist-info/WHEEL
isNumberFour-0.2.0.dist-info/top_level.txt
isNumberFour-0.2.0.dist-info/RECORD
